[
    {
        "name": "nativescript-angular",
        "directory": "..\\..\\node_modules\\nativescript-angular"
    },
    {
        "name": "nativescript-couchbase",
        "directory": "..\\..\\node_modules\\nativescript-couchbase"
    },
    {
        "name": "nativescript-gif",
        "directory": "..\\..\\node_modules\\nativescript-gif"
    },
    {
        "name": "nativescript-sqlite",
        "directory": "..\\..\\node_modules\\nativescript-sqlite"
    },
    {
        "name": "nativescript-theme-core",
        "directory": "..\\..\\node_modules\\nativescript-theme-core"
    },
    {
        "name": "nativescript-ui-listview",
        "directory": "..\\..\\node_modules\\nativescript-ui-listview"
    },
    {
        "name": "nativescript-uuid",
        "directory": "..\\..\\node_modules\\nativescript-uuid"
    },
    {
        "name": "tns-core-modules",
        "directory": "..\\..\\node_modules\\tns-core-modules"
    },
    {
        "name": "nativescript-intl",
        "directory": "..\\..\\node_modules\\nativescript-intl"
    },
    {
        "name": "nativescript-ui-core",
        "directory": "..\\..\\node_modules\\nativescript-ui-core"
    },
    {
        "name": "tns-core-modules-widgets",
        "directory": "..\\..\\node_modules\\tns-core-modules-widgets"
    }
]